ogd/apis/HelloAPI.py
ogd/apis/__init__.py
ogd/apis/configs/ServerConfig.py
ogd/apis/configs/__init__.py
ogd/apis/models/APIRequest.py
ogd/apis/models/APIResponse.py
ogd/apis/models/__init__.py
ogd/apis/models/enums/RESTType.py
ogd/apis/models/enums/ResponseStatus.py
ogd/apis/models/enums/__init__.py
ogd/apis/utils/APIUtils.py
ogd/apis/utils/__init__.py
opengamedata_api_utils-1.4.1.dist-info/LICENSE
opengamedata_api_utils-1.4.1.dist-info/METADATA
opengamedata_api_utils-1.4.1.dist-info/WHEEL
opengamedata_api_utils-1.4.1.dist-info/top_level.txt
opengamedata_api_utils-1.4.1.dist-info/RECORD
