Metadata-Version: 2.1
Name: opengamedata-api-utils
Version: 1.4.1
Summary: Package of utilities for server-side scripts in OpenGameData.
Author: Ryan Wilkinson, Glenn Palmer, Daus Husaini
Author-email: Luke Swanson <superscription58@gmail.com>
Project-URL: Homepage, https://github.com/opengamedata/opengamedata-api-utils
Project-URL: Bug Tracker, https://github.com/opengamedata/opengamedata-api-utils/issues
Classifier: Programming Language :: Python :: 3
Classifier: License :: OSI Approved :: MIT License
Classifier: Operating System :: OS Independent
Requires-Python: >=3.12
License-File: LICENSE
Requires-Dist: flask==2.3.3
Requires-Dist: flask-restful==0.3.10
Requires-Dist: requests==2.32.*
Requires-Dist: opengamedata-common==2.0.*
Requires-Dist: opengamedata-core==0.0.14
